pyLDLE2/gl_.py
pyLDLE2/global_reg_.py
pyLDLE2/global_views_.py
pyLDLE2/ldle_.py
pyLDLE2/local_views_.py
pyLDLE2/util_.py
pyLDLE2/visualize_.py
pyLDLE2/visualize_all.py
pyLDLE2-0.1.9.dist-info/LICENSE
pyLDLE2-0.1.9.dist-info/METADATA
pyLDLE2-0.1.9.dist-info/WHEEL
pyLDLE2-0.1.9.dist-info/top_level.txt
pyLDLE2-0.1.9.dist-info/RECORD
