Metadata-Version: 2.1
Name: pyLDLE2
Version: 0.1.9
Summary: Low Distortion Local Eigenmaps and its variations.
Author: Dhruv Kohli, Alex Cloninger, Gal Mishne
License: MIT License
Project-URL: Homepage, https://github.com/chiggum/pyLDLE2
Project-URL: Bug Tracker, https://github.com/chiggum/pyLDLE2/issues
Classifier: Programming Language :: Python :: 3
Classifier: License :: OSI Approved :: MIT License
Classifier: Operating System :: OS Independent
Requires-Python: >=3.8
License-File: LICENSE
